{
  "2021 NWAA Freaky Fast Last Cha": "2021 NWAA Freaky Fast Last Chance Meet",
  "2021 NWAA Friday Night Frenzy": "2021 NWAA Friday Night Frenzy",
  "2023 ARSI Long Course Champion": "2023 ARSI Long Course Championship",
  "2023 AquaHawgs Long Course Ope": "2023 AquaHawgs Long Course Open",
  "2024 ARSI Long Course Champion": "2024 ARSI Long Course Championship",
  "2024 Rose Memorial Invitationa": "2024 Rose Memorial Invitational",
  "2025 Arkansas Long Course Cham": "2025 Arkansas Long Course Championship",
  "2025 Arkansas Senior Champions": "2025 Arkansas Senior Championship",
  "2025 NWAA Memorial Classic 2.0": "2025 NWAA Memorial Classic 2.0",
  "2025 Spring Splash Invitationa": "2025 Spring Splash Invitational",
  "2026 AAA 6A West Conference Ch": "2026 AAA 6A West Conference Championship",
  "2026 Arkansas Senior Champions": "2026 Arkansas Senior Championship",
  "2026 Centennial Bank Arkansas": "2026 Centennial Bank Arkansas",
  "27th Annual NWAA Winter Invita": "27th Annual NWAA Winter Invitational",
  "28th Annual NWAA Winter Invita": "28th Annual NWAA Winter Invitational",
  "29th Annual NWAA Winter Invita": "29th Annual NWAA Winter Invitational",
  "30th Annual NWAA Winter Invita": "30th Annual NWAA Winter Invitational",
  "68th Annual Air Capital Invita": "68th Annual Air Capital Invitational",
  "ARSI 14 & Under Age Group Cham": "ARSI 14 & Under Age Group Championship",
  "Friday Night at the Races 23": "Friday Night at the Races 23",
  "Friday Night at the Races 24": "Friday Night at the Races 24",
  "Jenks Gobbler Invitational 202": "Jenks Gobbler Invitational 2024",
  "NWAA Freaky Fast Last Chance M": "NWAA Freaky Fast Last Chance Meet",
  "NWAA Friday Night Frenzy #10": "NWAA Friday Night Frenzy #10",
  "NWAA Friday Night Frenzy #11": "NWAA Friday Night Frenzy #11"
}